README
setup.py
django_reversetag.egg-info/PKG-INFO
django_reversetag.egg-info/SOURCES.txt
django_reversetag.egg-info/dependency_links.txt
django_reversetag.egg-info/top_level.txt
reversetag/__init__.py
reversetag/templatetags/__init__.py
reversetag/templatetags/reversetag.py
tests/test_settings.py
tests/revtest/__init__.py
tests/revtest/models.py
tests/revtest/urls.py
tests/revtest/views.py