Metadata-Version: 1.0
Name: django-reversetag
Version: 0.3.1
Summary: A new, improved (and renamed) implementation of Django's 'url' template tag.
Home-page: http://github.com/ulope/django-reversetag
Author: Ulrich Petri
Author-email: mail@ulo.pe
License: MIT
Keywords: django
Platform: UNKNOWN
